djangokarat/__init__.py
djangokarat/base.py
djangokarat/constraints.py
djangokarat/models.py
djangokarat/options.py
djangokarat/test.py
djangokarat/urls.py
djangokarat/utils.py
djangokarat/views.py
djangokarat-1.2.3.dist-info/METADATA
djangokarat-1.2.3.dist-info/RECORD
djangokarat-1.2.3.dist-info/WHEEL
djangokarat-1.2.3.dist-info/top_level.txt
