Metadata-Version: 2.1
Name: djangokarat
Version: 1.2.3
Summary: ability to create models with send/accept fields to/from karat DB
Home-page: https://kiwi.whys.eu/karaterp/axima-agent
Author: David Simonyi
Author-email: david@whys.eu
License: Creative Commons Attribution-Noncommercial-Share Alike license
Platform: UNKNOWN
Classifier: Programming Language :: Python :: 3
Classifier: Operating System :: OS Independent
